HISTORY.txt
LICENSE
MANIFEST.in
README.md
requirements.txt
setup.cfg
setup.py
rcsb/__init__.py
rcsb.app.file.egg-info/PKG-INFO
rcsb.app.file.egg-info/SOURCES.txt
rcsb.app.file.egg-info/dependency_links.txt
rcsb.app.file.egg-info/not-zip-safe
rcsb.app.file.egg-info/requires.txt
rcsb.app.file.egg-info/top_level.txt
rcsb/app/__init__.py
rcsb/app/client/ClientUtility.py
rcsb/app/client/__init__.py
rcsb/app/client/front-end/__init__.py
rcsb/app/client/front-end/client.py
rcsb/app/client/front-end/gui.py
rcsb/app/config/__init__.py
rcsb/app/config/setConfig.py
rcsb/app/file/ConfigProvider.py
rcsb/app/file/Definitions.py
rcsb/app/file/DownloadUtility.py
rcsb/app/file/IoUtility.py
rcsb/app/file/JWTAuthBearer.py
rcsb/app/file/JWTAuthToken.py
rcsb/app/file/KvBase.py
rcsb/app/file/KvConnection.py
rcsb/app/file/KvRedis.py
rcsb/app/file/KvSqlite.py
rcsb/app/file/PathProvider.py
rcsb/app/file/RedisLock.py
rcsb/app/file/Sessions.py
rcsb/app/file/SoftLock.py
rcsb/app/file/TernaryLock.py
rcsb/app/file/UploadUtility.py
rcsb/app/file/__init__.py
rcsb/app/file/downloadRequest.py
rcsb/app/file/ioRequest.py
rcsb/app/file/main.py
rcsb/app/file/pathRequest.py
rcsb/app/file/serverStatus.py
rcsb/app/file/serverStatusRequest.py
rcsb/app/file/tokenRequest.py
rcsb/app/file/uploadRequest.py