Metadata-Version: 2.1
Name: rcsb.app.file
Version: 1.3.2
Summary: RCSB File Access Service Application
Home-page: https://github.com/rcsb/py-rcsb_app_file
Author: John Westbrook
Author-email: john.westbrook@rcsb.org
License: Apache 2.0
Classifier: Development Status :: 3 - Alpha
Classifier: Intended Audience :: Developers
Classifier: Natural Language :: English
Classifier: License :: OSI Approved :: Apache Software License
Classifier: Programming Language :: Python
Classifier: Programming Language :: Python :: 3
Classifier: Programming Language :: Python :: 3.9
License-File: LICENSE
Requires-Dist: gunicorn>=20.0.4
Requires-Dist: fastapi~=0.109.2
Requires-Dist: starlette~=0.36.3
Requires-Dist: python-multipart~=0.0.7
Requires-Dist: pydantic~=1.10.2
Requires-Dist: uvicorn[standard]>=0.12.0
Requires-Dist: rcsb.utils.config>=0.36
Requires-Dist: rcsb.utils.io>=1.22
Requires-Dist: mmcif>=0.71
Requires-Dist: setuptools~=60.2.0
Requires-Dist: requests~=2.28.1
Requires-Dist: aiofiles>=0.5.0
Requires-Dist: aiohttp
Requires-Dist: redis~=5.0.1
Requires-Dist: redis-server
Requires-Dist: Pillow~=10.0.1
Requires-Dist: tqdm~=4.66.1
Requires-Dist: httpx
Requires-Dist: PyJWT~=2.8.0
Requires-Dist: future~=0.18.3
Requires-Dist: psutil~=5.9.5
Requires-Dist: validators>=0.22.0
Provides-Extra: dev
Requires-Dist: check-manifest; extra == "dev"
Provides-Extra: test
Requires-Dist: coverage; extra == "test"
